ademapkit/__init__.py
ademapkit/ademapkit.db
ademapkit/map/__init__.py
ademapkit/map/country_script.py
ademapkit/map/usa_cities_script.py
ademapkit/model/__init__.py
ademapkit/model/country_model.py
ademapkit/model/usa_cities_details_model.py
ademapkit/model/usa_cities_model.py
ademapkit-0.0.5.dist-info/licenses/LICENSE
ademapkit-0.0.5.dist-info/METADATA
ademapkit-0.0.5.dist-info/WHEEL
ademapkit-0.0.5.dist-info/top_level.txt
ademapkit-0.0.5.dist-info/RECORD
