Metadata-Version: 2.4
Name: ademapkit
Version: 0.0.5
Summary: This is a package for all the countries in the world
Author-email: Abdullah Adesina Dhikrullah <daadesina1@gmail.com>
License: Built by Abdullah Adesina Dhikrullah
Requires-Python: >=3.10
License-File: LICENSE
Requires-Dist: requests
Dynamic: license-file
